tabulato/__init__.py
tabulato/table.py
tabulato/utils.py
tabulato/tests/test_tables.py
tabulato-1.0.4.dist-info/LICENSE
tabulato-1.0.4.dist-info/METADATA
tabulato-1.0.4.dist-info/WHEEL
tabulato-1.0.4.dist-info/top_level.txt
tabulato-1.0.4.dist-info/RECORD
